liblds/__init__.py
liblds/calibration.py
liblds/checksum.py
liblds/converters.py
liblds/lds_descriptors.py
liblds/lds_logging.py
liblds/ldsbus_commands.py
liblds/ldsbus_constants.py
liblds/ldsbus_interface.py
liblds/ldsbus_interface_messages.py
liblds/liblds.py
lada-0.0.1.dist-info/METADATA
lada-0.0.1.dist-info/WHEEL
lada-0.0.1.dist-info/top_level.txt
lada-0.0.1.dist-info/RECORD
