Metadata-Version: 2.1
Name: lada
Version: 0.0.1
Summary: Python Library for LDSBus Devices
Home-page: http://www.brtsys.com
Author: Prabhakaran Dharmarajan
Author-email: prabhakaran.d@brtchip.com
License: MIT
Platform: UNKNOWN
Requires-Dist: logging
Requires-Dist: coloredlogs
Requires-Dist: ftd2xx
